tencentcloud/__init__.py
tencentcloud/tke/__init__.py
tencentcloud/tke/v20180525/__init__.py
tencentcloud/tke/v20180525/errorcodes.py
tencentcloud/tke/v20180525/models.py
tencentcloud/tke/v20180525/tke_client.py
tencentcloud/tke/v20180525/tke_client_async.py
tencentcloud/tke/v20220501/__init__.py
tencentcloud/tke/v20220501/errorcodes.py
tencentcloud/tke/v20220501/models.py
tencentcloud/tke/v20220501/tke_client.py
tencentcloud/tke/v20220501/tke_client_async.py
tencentcloud_sdk_python_tke-3.1.32.dist-info/METADATA
tencentcloud_sdk_python_tke-3.1.32.dist-info/WHEEL
tencentcloud_sdk_python_tke-3.1.32.dist-info/top_level.txt
tencentcloud_sdk_python_tke-3.1.32.dist-info/RECORD
